sinetstream/__init__.py
sinetstream/__main__.py
sinetstream/api.py
sinetstream/codec.py
sinetstream/compression.py
sinetstream/config_client.py
sinetstream/configs.py
sinetstream/crypto.py
sinetstream/error.py
sinetstream/marshal.py
sinetstream/packet.py
sinetstream/pylintrc
sinetstream/spi.py
sinetstream/utils.py
sinetstream/value_type.py
sinetstream-1.9.2.dist-info/METADATA
sinetstream-1.9.2.dist-info/WHEEL
sinetstream-1.9.2.dist-info/RECORD
