Metadata-Version: 2.4
Name: sinetstream
Version: 1.9.2
Summary: Library for operating messaging systems such as Apache Kafka and MQTT with the same API.
Project-URL: Documentation, https://www.sinetstream.net/
Project-URL: Repository, https://github.com/nii-gakunin-cloud/sinetstream.git
License: Apache License, Version 2.0
Classifier: Intended Audience :: Developers
Classifier: License :: OSI Approved :: Apache Software License
Classifier: Programming Language :: Python :: 3 :: Only
Classifier: Topic :: Software Development :: Libraries :: Python Modules
Requires-Python: >=3.9
Requires-Dist: avro-python3
Requires-Dist: promise
Requires-Dist: pycryptodomex
Requires-Dist: pyyaml
Requires-Dist: requests
Requires-Dist: zstandard
